autoexplain/__init__.py
autoexplain/autoexplain.py
autoexplain/subcommands.py
constants/__init__.py
constants/aexp_constants.py
constants/prompts.py
functions/__init__.py
functions/openai_functions.py
utils/__init__.py
utils/utils.py
autoexplain-1.1.3.dist-info/LICENSE
autoexplain-1.1.3.dist-info/METADATA
autoexplain-1.1.3.dist-info/WHEEL
autoexplain-1.1.3.dist-info/entry_points.txt
autoexplain-1.1.3.dist-info/top_level.txt
autoexplain-1.1.3.dist-info/RECORD
